setup.py
spreadscript/__init__.py
spreadscript/cli.py
spreadscript/spreadscript.py
spreadscript.egg-info/PKG-INFO
spreadscript.egg-info/SOURCES.txt
spreadscript.egg-info/dependency_links.txt
spreadscript.egg-info/entry_points.txt
spreadscript.egg-info/requires.txt
spreadscript.egg-info/top_level.txt