Metadata-Version: 1.1
Name: spreadscript
Version: 0.0.3
Summary: spreadscript: Use a spreadsheet as a function.
Home-page: https://github.com/jfjlaros/spreadscript
Author: Jeroen F.J. Laros
Author-email: jlaros@fixedpoint.nl
License: MIT License
Platform: any
Classifier: Development Status :: 3 - Alpha
Classifier: Intended Audience :: Science/Research
Classifier: Intended Audience :: Developers
Classifier: Topic :: Scientific/Engineering
Classifier: License :: OSI Approved :: MIT License
Classifier: Operating System :: OS Independent
Classifier: Programming Language :: Python
Classifier: Programming Language :: Python :: 3
Classifier: Programming Language :: Python :: 3
Classifier: Programming Language :: Python :: 3.5
